cerebromcp/__init__.py
cerebromcp/clients/__init__.py
cerebromcp/clients/crewai_client.py
cerebromcp/clients/llama_client.py
cerebromcp/clients/openai_client.py
cerebromcp/clients/rag_client.py
cerebromcp/host_managed/__init__.py
cerebromcp/host_managed/internal_llm.py
cerebromcp/main.py
cerebromcp/memory/__init__.py
cerebromcp/memory/sqlite_memory.py
cerebromcp/servers/__init__.py
cerebromcp/servers/crewai_server.py
cerebromcp/servers/llama_server.py
cerebromcp/servers/openai_server.py
cerebromcp/servers/persistent_server.py
cerebromcp/servers/rag_mcp_server.py
cerebromcp-0.1.0.dist-info/METADATA
cerebromcp-0.1.0.dist-info/WHEEL
cerebromcp-0.1.0.dist-info/RECORD
