Metadata-Version: 2.3
Name: cerebromcp
Version: 0.1.0
Summary: Intelligent AI Orchestration at Your Fingertips - A powerful system that combines the best of multiple AI technologies to deliver smart, context-aware responses
License: MIT
Author: Prahlad Inala
Author-email: prahlad.inala@gmail.com
Requires-Python: >=3.10,<4.0
Classifier: License :: OSI Approved :: MIT License
Classifier: Programming Language :: Python :: 3
Classifier: Programming Language :: Python :: 3.10
Classifier: Programming Language :: Python :: 3.11
Classifier: Programming Language :: Python :: 3.12
Classifier: Programming Language :: Python :: 3.13
Requires-Dist: aiohttp (>=3.8.0,<4.0.0)
Requires-Dist: aiosqlite (>=0.19.0,<0.20.0)
Requires-Dist: chromadb (>=0.4.0,<0.5.0)
Requires-Dist: crewai (>=0.11.0,<0.12.0)
Requires-Dist: langchain (>=0.1.0,<0.2.0)
Requires-Dist: langgraph (>=0.0.10,<0.0.11)
Requires-Dist: mcp (>=1.9.0,<2.0.0)
Requires-Dist: openai (>=1.0.0,<2.0.0)
Requires-Dist: pydantic (>=2.0.0,<3.0.0)
Requires-Dist: python-dotenv (>=1.0.0,<2.0.0)
Requires-Dist: typing-extensions (>=4.5.0,<5.0.0)
